jzip/__init__.py
jzip/_jzip.cpython-310-x86_64-linux-gnu.so
jzip/_jzip.pyi
jzip/py.typed
src/main.zig
src/python.zig
tests/test_c_compat.py
tests/test_decompression.py
tests/test_roundtrip.py
jzip_zig-0.0.8.dist-info/METADATA
jzip_zig-0.0.8.dist-info/WHEEL
jzip_zig-0.0.8.dist-info/top_level.txt
jzip_zig-0.0.8.dist-info/RECORD
jzip_zig-0.0.8.dist-info/licenses/LICENSE
jzip_zig-0.0.8.dist-info/licenses/third_party/zstd/LICENSE
