Metadata-Version: 2.4
Name: jzip-zig
Version: 0.0.8
Summary: Python bindings for jzip (Zig) - near-lossless embedding compression
License-Expression: MIT
Keywords: compression,embeddings,zstd,zig
Classifier: Development Status :: 3 - Alpha
Classifier: Programming Language :: Python :: 3
Classifier: Topic :: System :: Archiving :: Compression
Requires-Python: >=3.10
License-File: LICENSE
License-File: third_party/zstd/LICENSE
Requires-Dist: numpy
Dynamic: license-file
